cuv/README.rst
cuv/__init__.py
cuv/__main__.py
cuv/_version.py
cuv/analysis.py
cuv/cli.py
cuv/click_autodoc.py
cuv/diff.py
cuv/graph.py
cuv/less.py
cuv/source-code-pro.ttf
cuv/spark.py
cuv/util.py
cuv/watch.py
cuvner-24.12.1.dist-info/METADATA
cuvner-24.12.1.dist-info/WHEEL
cuvner-24.12.1.dist-info/entry_points.txt
cuvner-24.12.1.dist-info/licenses/LICENSE
cuvner-24.12.1.dist-info/RECORD
